aquilify/__global.py
aquilify/__init__.py
aquilify/__version__.py
aquilify/config.py
aquilify/py.typed
aquilify/responses.py
aquilify/shortcuts.py
aquilify/types.py
aquilify/build/__init__.py
aquilify/build/b9IN.py
aquilify/build/insecure.py
aquilify/build/fax/__init__.py
aquilify/build/fax/__root__.py
aquilify/build/fax/asgi.py
aquilify/build/fax/ax.py
aquilify/build/fax/models.py
aquilify/build/fax/routing.py
aquilify/build/fax/settings.py
aquilify/build/fax/setup.py
aquilify/build/fax/tools.py
aquilify/build/fax/views.py
aquilify/build/fax/app/__init__.py
aquilify/build/fax/app/main.py
aquilify/build/fax/lifespan/__init__.py
aquilify/core/__globals.py
aquilify/core/__init__.py
aquilify/core/__status.py
aquilify/core/_apptest.py
aquilify/core/_logging.py
aquilify/core/_routing.py
aquilify/core/application.py
aquilify/core/converter.py
aquilify/core/mailer.py
aquilify/core/routing.py
aquilify/core/sessions.py
aquilify/core/signing.py
aquilify/core/status.py
aquilify/core/asgi/__init__.py
aquilify/core/asgi/application.py
aquilify/core/asgi/asgi_middleware.py
aquilify/core/asgi/routes.py
aquilify/core/backend/__init__.py
aquilify/core/backend/sessions/__init__.py
aquilify/core/backend/sessions/cookiesession.py
aquilify/core/backend/sessions/inmemorysession.py
aquilify/core/backend/sessions/localsessions.py
aquilify/core/backend/sessions/storage/__init__.py
aquilify/core/backend/sessions/storage/cookie.py
aquilify/core/backend/sessions/storage/memory.py
aquilify/core/backend/syncbit/__init__.py
aquilify/core/backend/syncbit/configs.py
aquilify/core/backend/syncbit/contexts.py
aquilify/core/backend/syncbit/exceptions.py
aquilify/core/backend/syncbit/schema.py
aquilify/core/backend/syncbit/type_validation.py
aquilify/core/backend/syncbit/utils.py
aquilify/core/backend/syncbit/validate.py
aquilify/core/backend/syncbit/fields/__init__.py
aquilify/core/backend/syncbit/fields/base.py
aquilify/core/backend/syncbit/fields/nesting.py
aquilify-1.17.dist-info/LICENSE
aquilify-1.17.dist-info/METADATA
aquilify-1.17.dist-info/WHEEL
aquilify-1.17.dist-info/entry_points.txt
aquilify-1.17.dist-info/top_level.txt
aquilify-1.17.dist-info/RECORD
