Metadata-Version: 2.1
Name: aquilify
Version: 1.17
Summary: Aquilify is an ASGI (Asynchronous Server Gateway Interface) framework designed to facilitate the development of web applications with Python. It enables efficient handling of HTTP requests, WebSocket connections, middleware processing, and exception handling in an asynchronous environment.
Home-page: https://github.com/embrake/aquilify/
Author: Pawan kumar
Author-email: embrakeproject@gmail.com
License: BSD-3-Clause
Keywords: web framework,Python web development,user-friendly,high-level,ASGI,backend
Classifier: Development Status :: 5 - Production/Stable
Classifier: Framework :: AsyncIO
Classifier: Intended Audience :: Developers
Classifier: Topic :: Internet :: WWW/HTTP :: HTTP Servers
Classifier: License :: OSI Approved :: BSD License
Classifier: Programming Language :: Python :: 3
Classifier: Programming Language :: Python :: 3.6
Classifier: Programming Language :: Python :: 3.7
Classifier: Programming Language :: Python :: 3.8
Classifier: Programming Language :: Python :: 3.9
License-File: LICENSE
Requires-Dist: anyio
Requires-Dist: pymysql
Provides-Extra: full
Requires-Dist: jinja2 ; extra == 'full'
Requires-Dist: aiofiles ; extra == 'full'
Requires-Dist: python-multipart ; extra == 'full'
Requires-Dist: markupsafe ; extra == 'full'
Provides-Extra: sec
Requires-Dist: aiofiles ; extra == 'sec'
Requires-Dist: markupsafe ; extra == 'sec'
Provides-Extra: template
Requires-Dist: jinja2 ; extra == 'template'
Requires-Dist: aiofiles ; extra == 'template'
